README.md
setup.py
okeydokey/__init__.py
okeydokey.egg-info/PKG-INFO
okeydokey.egg-info/SOURCES.txt
okeydokey.egg-info/dependency_links.txt
okeydokey.egg-info/requires.txt
okeydokey.egg-info/top_level.txt
okeydokey/notifier/Telegram.py
okeydokey/notifier/__init__.py
okeydokey/notifier/notifier.py