Metadata-Version: 1.0
Name: okeydokey
Version: 0.1.0
Summary: Notify on shared password retrieval
Home-page: https://github.com/droberin/notary
Author: Roberto Salgado
Author-email: drober@gmail.com
License: MIT
Platform: UNKNOWN
